doublerun/pandas.py
doublerun/spark.py
doublerun-0.0.3.dist-info/METADATA
doublerun-0.0.3.dist-info/WHEEL
doublerun-0.0.3.dist-info/top_level.txt
doublerun-0.0.3.dist-info/RECORD
