Metadata-Version: 2.1
Name: doublerun
Version: 0.0.3
Requires-Python: <3.12,>=3.7
Requires-Dist: pandas ==1.5.1
Requires-Dist: pyspark ==3.3.2
Provides-Extra: dev
Requires-Dist: ruff ==0.0.292 ; extra == 'dev'
Requires-Dist: black ==23.9.1 ; extra == 'dev'
Requires-Dist: pytest ==7.4.2 ; extra == 'dev'
Requires-Dist: pytest-cov ==4.1.0 ; extra == 'dev'
